extype.libs/libstdc++-8baf04f9.so.6.0.28
extype.libs/libgcc_s-8b50eaaa.so.1
extype/extension_utils.py
extype/core.cpython-310-i386-linux-gnu.so
extype/__init__.py
extype/builtin_extensions/int_ext.py
extype/builtin_extensions/list_ext.py
extype/builtin_extensions/seq_ext.py
extype/builtin_extensions/float_ext.py
extype/builtin_extensions/dict_ext.py
extype/builtin_extensions/str_ext.py
extype/builtin_extensions/function_ext.py
extype/builtin_extensions/extend_all.py
extype/builtin_extensions/__init__.py
extype-1.1.1.dist-info/RECORD
extype-1.1.1.dist-info/METADATA
extype-1.1.1.dist-info/WHEEL
