Metadata-Version: 2.1
Name: extype
Version: 1.1.1
Summary: ExType is a Python package that allows you to externally extend types.
Author-Email: Xpo Development <dev@xpo.dev>, Elazar Cohen <elazarcoh@gmail.com>
Requires-Python: >=3.7
